leoss/__init__.py
leoss/live.py
leoss/main.py
leoss/visual.py
leoss-0.4.0.dist-info/METADATA
leoss-0.4.0.dist-info/WHEEL
leoss-0.4.0.dist-info/RECORD
