Metadata-Version: 2.1
Name: leoss
Version: 0.4.0
Summary: Low Earth Orbit Spacecraft Simulator
License: MIT
Author: space-hiro
Author-email: 144877753+space-hiro@users.noreply.github.com
Requires-Python: >=3.10,<3.13
Classifier: License :: OSI Approved :: MIT License
Classifier: Programming Language :: Python :: 3
Classifier: Programming Language :: Python :: 3.10
Classifier: Programming Language :: Python :: 3.11
Requires-Dist: cartopy (>=0.22.0,<0.23.0)
Requires-Dist: datetime (>=5.2,<6.0)
Requires-Dist: matplotlib (>=3.8.0,<4.0.0)
Requires-Dist: numpy (<2)
Requires-Dist: pandas (>=2.1.1,<3.0.0)
Requires-Dist: pyigrf (>=0.3.3,<0.4.0)
Requires-Dist: tqdm (>=4.66.1,<5.0.0)
